pydynsm/__init__.py
pydynsm/assembler.py
pydynsm/__pycache__/__init__.cpython-311.pyc
pydynsm/__pycache__/assembler.cpython-311.pyc
pydynsm/analysis/__init__.py
pydynsm/analysis/analysis.py
pydynsm/analysis/dofs.py
pydynsm/analysis/element.py
pydynsm/analysis/node.py
pydynsm/analysis/__pycache__/__init__.cpython-311.pyc
pydynsm/analysis/__pycache__/analysis.cpython-311.pyc
pydynsm/analysis/__pycache__/dofs.cpython-311.pyc
pydynsm/analysis/__pycache__/element.cpython-311.pyc
pydynsm/analysis/__pycache__/node.cpython-311.pyc
pydynsm/elements/1Drod_foundation.png
pydynsm/elements/__init__.py
pydynsm/elements/eb_beam.py
pydynsm/elements/eb_beam_exp.py
pydynsm/elements/eb_beam_foundation.py
pydynsm/elements/eb_beam_foundation_end_attachment.py
pydynsm/elements/eb_beam_tensioned.py
pydynsm/elements/example.py
pydynsm/elements/rayleigh_beam.py
pydynsm/elements/rb_rod.py
pydynsm/elements/rl_rod.py
pydynsm/elements/rod_1D_exp.py
pydynsm/elements/rod_1D_foundation.py
pydynsm/elements/rod_1d.py
pydynsm/elements/shear_beam_1D_exp.py
pydynsm/elements/structuralelement.py
pydynsm/elements/timoshenko_beam.py
pydynsm/elements/__pycache__/__init__.cpython-311.pyc
pydynsm/elements/__pycache__/eb_beam_exp.cpython-311.pyc
pydynsm/elements/__pycache__/eb_beam_foundation.cpython-311.pyc
pydynsm/elements/__pycache__/eb_beam_foundation_end_attachment.cpython-311.pyc
pydynsm/elements/__pycache__/eb_beam_tensioned.cpython-311.pyc
pydynsm/elements/__pycache__/rayleigh_beam.cpython-311.pyc
pydynsm/elements/__pycache__/rb_rod.cpython-311.pyc
pydynsm/elements/__pycache__/rl_rod.cpython-311.pyc
pydynsm/elements/__pycache__/rod_1D_exp.cpython-311.pyc
pydynsm/elements/__pycache__/rod_1D_foundation.cpython-311.pyc
pydynsm/elements/__pycache__/shear_beam_1D_exp.cpython-311.pyc
pydynsm/elements/__pycache__/structuralelement.cpython-311.pyc
pydynsm/logging/__init__.py
pydynsm/logging/logger.py
pydynsm/plotter/__init__.py
pydynsm/plotter/structureplotter.py
pydynsm-0.2.6.dist-info/METADATA
pydynsm-0.2.6.dist-info/WHEEL
pydynsm-0.2.6.dist-info/top_level.txt
pydynsm-0.2.6.dist-info/RECORD
