Metadata-Version: 2.4
Name: PyDynSM
Version: 0.2.6
Summary: A Dynamic Stiffness Matrix method solver.
Author-email: Technical University Delft <r.j.vanleijden-1@tudelft.nl>
License: MIT License
Classifier: Programming Language :: Python :: 3
Classifier: License :: OSI Approved :: MIT License
Classifier: Operating System :: OS Independent
Requires-Python: >=3.10
Requires-Dist: numpy>=1.21
Requires-Dist: matplotlib>=3.4
Requires-Dist: scipy>=1.7
